synphage/__init__.py
synphage/jobs.py
synphage/assets/__init__.py
synphage/assets/blaster/__init__.py
synphage/assets/blaster/n_blaster.py
synphage/assets/blaster/n_parser.py
synphage/assets/blaster/p_blaster.py
synphage/assets/blaster/p_parser.py
synphage/assets/blaster/sql/__init__.py
synphage/assets/blaster/sql/gene_presence.sql
synphage/assets/blaster/sql/parse_blastn.sql
synphage/assets/ncbi_connect/__init__.py
synphage/assets/ncbi_connect/accession.py
synphage/assets/ncbi_connect/downloaded_file_transfer.py
synphage/assets/status/__init__.py
synphage/assets/status/content_loading.py
synphage/assets/status/content_validation.py
synphage/assets/status/external_code.py
synphage/assets/status/validated_content.py
synphage/assets/user_data/__init__.py
synphage/assets/user_data/users_file_transfer.py
synphage/assets/viewer/__init__.py
synphage/assets/viewer/static_graph.py
synphage/assets/viewer/template.svg
synphage/resources/__init__.py
synphage/resources/local_resource.py
synphage/resources/ncbi_resource.py
synphage/resources/parquet_io_manager.py
synphage/resources/s3_resource.py
synphage/sql/__init__.py
synphage/utils/__init__.py
synphage/utils/check_factory.py
synphage/utils/convert_gb_to_df.py
synphage/utils/reload_ui.py
synphage-0.2.7.dist-info/LICENSE
synphage-0.2.7.dist-info/METADATA
synphage-0.2.7.dist-info/WHEEL
synphage-0.2.7.dist-info/top_level.txt
synphage-0.2.7.dist-info/RECORD
