Metadata-Version: 2.1
Name: synphage
Version: 0.2.7
Summary: Python library for plotting synteny diagram for phage and bacterial sequences.
Author-email: Virginie Grosboillot <vestalisvirginis@gmail.com>
License: Apache License
Project-URL: Homepage, https://github.com/vestalisvirginis/synphage
Project-URL: Bug Tracker, https://github.com/vestalisvirginis/synphage
Classifier: Programming Language :: Python :: 3
Classifier: License :: OSI Approved :: Apache Software License
Classifier: Operating System :: OS Independent
Requires-Python: >=3.11
License-File: LICENSE
Requires-Dist: dagster ==1.7.15
Requires-Dist: dagster-webserver ==1.7.15
Requires-Dist: biopython ==1.84
Requires-Dist: reportlab ==4.2.2
Requires-Dist: rlPyCairo ==0.3.0
Requires-Dist: cuallee ==0.13.1
Requires-Dist: pandas ==2.2.2
Requires-Dist: duckdb ==1.0.0
Requires-Dist: polars ==1.3.0
Requires-Dist: pyarrow ==17.0.0
Requires-Dist: requests ==2.32.3
Requires-Dist: pycairo ==1.26.1
Requires-Dist: svgutils ==0.3.4
Requires-Dist: cairosvg ==2.7.1
Provides-Extra: all
Requires-Dist: synphage[dev,test] ; extra == 'all'
Provides-Extra: dev
Requires-Dist: black ==24.4.2 ; extra == 'dev'
Requires-Dist: mypy ; extra == 'dev'
Requires-Dist: flake8 ; extra == 'dev'
Provides-Extra: test
Requires-Dist: pytest ; extra == 'test'
Requires-Dist: pytest-cov ; extra == 'test'
Requires-Dist: coverage ; extra == 'test'
